discretisedfield/__init__.py
discretisedfield/field.py
discretisedfield/field_rotator.py
discretisedfield/interact.py
discretisedfield/line.py
discretisedfield/mesh.py
discretisedfield/operators.py
discretisedfield/region.py
discretisedfield/html/__init__.py
discretisedfield/html/templates/__init__.py
discretisedfield/html/templates/field.jinja2
discretisedfield/html/templates/field_rotator.jinja2
discretisedfield/html/templates/mesh.jinja2
discretisedfield/html/templates/region.jinja2
discretisedfield/io/__init__.py
discretisedfield/io/hdf5.py
discretisedfield/io/ovf.py
discretisedfield/io/ovf2vtk.py
discretisedfield/io/vtk.py
discretisedfield/plotting/__init__.py
discretisedfield/plotting/hv.py
discretisedfield/plotting/k3d_field.py
discretisedfield/plotting/k3d_mesh.py
discretisedfield/plotting/k3d_region.py
discretisedfield/plotting/mpl.py
discretisedfield/plotting/mpl_field.py
discretisedfield/plotting/mpl_mesh.py
discretisedfield/plotting/mpl_region.py
discretisedfield/plotting/plotting-style.mplstyle
discretisedfield/plotting/pyvista_field.py
discretisedfield/plotting/pyvista_mesh.py
discretisedfield/plotting/pyvista_region.py
discretisedfield/plotting/util.py
discretisedfield/tests/__init__.py
discretisedfield/tests/conftest.py
discretisedfield/tests/test_field.py
discretisedfield/tests/test_field_rotator.py
discretisedfield/tests/test_init.py
discretisedfield/tests/test_interact.py
discretisedfield/tests/test_line.py
discretisedfield/tests/test_mesh.py
discretisedfield/tests/test_operators.py
discretisedfield/tests/test_ovf2vtk.py
discretisedfield/tests/test_plotting.py
discretisedfield/tests/test_region.py
discretisedfield/tests/test_tools.py
discretisedfield/tests/test_util.py
discretisedfield/tests/test_sample/demag_field_plane.omf
discretisedfield/tests/test_sample/demag_field_sphere.omf
discretisedfield/tests/test_sample/demag_tensor_oommf.omf
discretisedfield/tests/test_sample/hdf5-file.hdf5
discretisedfield/tests/test_sample/mumax-bin4-linux.ovf
discretisedfield-0.92.0.dist-info/licenses/LICENSE
discretisedfield-0.92.0.dist-info/METADATA
discretisedfield-0.92.0.dist-info/WHEEL
discretisedfield-0.92.0.dist-info/entry_points.txt
discretisedfield-0.92.0.dist-info/top_level.txt
discretisedfield-0.92.0.dist-info/RECORD
