Metadata-Version: 2.4
Name: discretisedfield
Version: 0.92.0
Summary: Python package for the analysis and visualisation of finite-difference fields.
Author: Marijan Beg, Martin Lang, Samuel Holt, Swapneel Amit Pathak, Ryan A. Pepper, Hans Fangohr
License-Expression: BSD-3-Clause
Project-URL: homepage, https://ubermag.github.io
Project-URL: documentation, https://ubermag.github.io/documentation/discretisedfield
Project-URL: repository, https://github.com/ubermag/discretisedfield
Classifier: Development Status :: 5 - Production/Stable
Classifier: Intended Audience :: Education
Classifier: Intended Audience :: Developers
Classifier: Intended Audience :: Science/Research
Classifier: Natural Language :: English
Classifier: Operating System :: MacOS
Classifier: Operating System :: Microsoft :: Windows
Classifier: Operating System :: Unix
Classifier: Programming Language :: Python :: 3 :: Only
Classifier: Topic :: Scientific/Engineering :: Physics
Classifier: Topic :: Scientific/Engineering :: Mathematics
Classifier: Topic :: Scientific/Engineering :: Visualization
Requires-Python: >=3.9
License-File: LICENSE
Requires-Dist: h5py>=3.1
Requires-Dist: holoviews
Requires-Dist: jinja2
Requires-Dist: k3d>=2.11
Requires-Dist: matplotlib!=3.7.2,>=3.3
Requires-Dist: pandas>=1.1
Requires-Dist: scipy>=1.6
Requires-Dist: sympy>=1.10.1
Requires-Dist: ubermagutil>=0.64.0
Requires-Dist: vtk>=9.1
Requires-Dist: xarray
Requires-Dist: pyvista[all]>=0.42.3
Provides-Extra: dev
Requires-Dist: build; extra == "dev"
Requires-Dist: invoke; extra == "dev"
Requires-Dist: nbval; extra == "dev"
Requires-Dist: pre-commit; extra == "dev"
Requires-Dist: pytest-cov; extra == "dev"
Requires-Dist: twine; extra == "dev"
Requires-Dist: tomli; python_version < "3.11" and extra == "dev"
Dynamic: license-file
